Metadata-Version: 1.1
Name: pqlpython3
Version: 0.5.0
Summary: A python expression to MongoDB query translator
Home-page: https://github.com/maimike/pql
Author: Alon Horev
Author-email: alon@horev.net
License: BSD
Download-URL: https://codeload.github.com/maimike/pql/zip/master
Platform: UNKNOWN
Classifier: Development Status :: 3 - Alpha
Classifier: Intended Audience :: Developers
Classifier: Programming Language :: Python :: 3.3
Classifier: Programming Language :: Python :: 3.5
Classifier: Operating System :: POSIX :: Linux
Classifier: Operating System :: MacOS :: MacOS X
